<PAMDataset>
  <PAMRasterBand band="1">
    <Histograms>
      <HistItem>
        <HistMin>2103.9453125</HistMin>
        <HistMax>2451.3056640625</HistMax>
        <BucketCount>256</BucketCount>
        <IncludeOutOfRange>1</IncludeOutOfRange>
        <Approximate>0</Approximate>
        <HistCounts>1497|2748|3522|5389|7882|12501|14177|11565|11889|13123|14599|15212|16673|15177|16685|17484|22410|25313|21933|19678|20102|22235|23887|27697|29537|31563|35252|35638|35648|39365|37358|37149|34451|28749|28725|30020|31238|37131|34790|33172|33119|34800|35849|33960|32118|31371|29836|29113|28614|28513|28238|27453|26646|25953|25390|24917|24655|24407|24045|23651|23281|22732|22274|21794|21603|21421|21304|21367|21362|21281|21248|21082|21033|20965|20898|20820|20653|20577|20415|20333|20151|20080|20059|19960|19742|19667|19404|19383|19202|19130|19020|19256|19057|19160|19136|19100|19119|19248|19197|19368|19487|19666|19776|20249|21174|21316|20513|19817|19447|19091|18830|18438|18308|18039|17768|17471|17331|17204|14493|14506|14373|14408|14268|14207|14151|14170|14025|14087|13951|13915|13929|13859|13794|13768|13692|13630|13621|13534|13566|13517|13435|13372|13292|13181|13221|13072|13099|12991|12949|12859|13818|14248|14228|14237|14237|14191|14207|14227|14207|14173|14182|14193|14137|14201|14275|14159|14239|14199|14246|14170|14227|14225|14204|14224|14212|14259|14319|14287|14315|14207|14304|14380|14259|14311|14313|14275|14381|14375|14482|14227|14156|14022|13956|13955|13860|13772|13668|13612|13611|13649|13421|13052|12976|12907|12735|12511|12470|12350|12214|12074|11988|12602|13298|13418|13017|12669|12682|12569|12424|12327|12436|12692|12334|11350|10921|10407|10052|9759|9489|9243|8898|8746|8505|8615|8411|8437|8382|7900|10365|8028|7802|7116|6175|4713|4371|3061|2740|1726|1038|759|642|539|505|414|213|1</HistCounts>
      </HistItem>
    </Histograms>
    <Metadata>
      <MDI key="STATISTICS_MINIMUM">2103.9453125</MDI>
      <MDI key="STATISTICS_MAXIMUM">2451.3056640625</MDI>
      <MDI key="STATISTICS_MEAN">2245.4221608868</MDI>
      <MDI key="STATISTICS_STDDEV">90.658513878708</MDI>
      <MDI key="STATISTICS_MEDIAN">2227.905281</MDI>
      <MDI key="STATISTICS_COUNT">4271864.000000</MDI>
      <MDI key="STATISTICS_SKIPFACTORX">1</MDI>
      <MDI key="STATISTICS_SKIPFACTORY">1</MDI>
      <MDI key="STATISTICS_EXCLUDEDVALUES"></MDI>
      <MDI key="STATISTICS_COVARIANCES">8218.966138695894</MDI>
    </Metadata>
  </PAMRasterBand>
</PAMDataset>
